zjuintl_assistant/__init__.py
zjuintl_assistant/assistant.py
zjuintl_assistant/constants.py
zjuintl_assistant/data_classes.py
zjuintl_assistant/login_utils.py
zjuintl_assistant-0.0.3.dist-info/LICENSE
zjuintl_assistant-0.0.3.dist-info/METADATA
zjuintl_assistant-0.0.3.dist-info/WHEEL
zjuintl_assistant-0.0.3.dist-info/top_level.txt
zjuintl_assistant-0.0.3.dist-info/RECORD
