Metadata-Version: 2.1
Name: zjuintl_assistant
Version: 0.0.3
Summary: Python interface for getting data from different platforms of ZJU International College
Home-page: https://github.com/ZJUIntl-share/zjuintl_assistant
Author: ZJUIntl-share
License: MIT
Requires-Python: >=3.6
License-File: LICENSE
Requires-Dist: rsa
Requires-Dist: requests
Requires-Dist: beautifulsoup4
